thai_lcc/__init__.py
thai_lcc/main.py
thai_lcc-0.0.3.dist-info/METADATA
thai_lcc-0.0.3.dist-info/WHEEL
thai_lcc-0.0.3.dist-info/top_level.txt
thai_lcc-0.0.3.dist-info/RECORD
