Metadata-Version: 2.4
Name: thai_lcc
Version: 0.0.3
Dynamic: description
Dynamic: description-content-type
